link/__init__.py
link/fulltext/__init__.py
link/fulltext/feature.py
link/fulltext/filter.py
link/fulltext/test/__init__.py
link/fulltext/test/filter.py
link.fulltext-0.9.dist-info/DESCRIPTION.rst
link.fulltext-0.9.dist-info/METADATA
link.fulltext-0.9.dist-info/RECORD
link.fulltext-0.9.dist-info/WHEEL
link.fulltext-0.9.dist-info/metadata.json
link.fulltext-0.9.dist-info/top_level.txt
