Metadata-Version: 2.0
Name: link.fulltext
Version: 0.9
Summary: Middleware feature for generic Fulltext-Index manipulation
Home-page: https://github.com/linkdd/link.fulltext
Author: David Delassus
Author-email: david.jose.delassus@gmail.com
License: MIT
Keywords: link fulltext index
Platform: UNKNOWN
Classifier: Development Status :: 5 - Production/Stable
Classifier: License :: OSI Approved :: MIT License
Classifier: Operating System :: OS Independent
Classifier: Topic :: Utilities
Classifier: Topic :: Software Development :: Libraries :: Python Modules
Classifier: Intended Audience :: Developers
Classifier: Programming Language :: Python
Classifier: Programming Language :: Python :: 2.7
Classifier: Programming Language :: Python :: 3
Classifier: Programming Language :: Python :: 3.4
Classifier: Programming Language :: Python :: 3.5
Classifier: Programming Language :: Python :: Implementation :: CPython
Requires-Dist: link.feature (>=2.1)
Requires-Dist: link.utils (>=2.0)
